shift_register-test.v
// tb_shift_reg.v — Unit test for the FIR shift register (delay line)
// Run: iverilog -g2012 -o tb_shift_reg tb_shift_reg.v && vvp tb_shift_reg

`default_nettype none
`timescale 1ns/1ps

// ── Shift register DUT (extracted from fir_filter.v) ──────────────────────
// If you later pull this into its own file, replace this block with:
//   `include "shift_reg.v"
module shift_reg #(
    parameter TAPS       = 16,
    parameter DATA_WIDTH = 16
) (
    input  wire                          clk,
    input  wire                          rst_n,
    input  wire signed [DATA_WIDTH-1:0]  d_in,
    input  wire                          valid_in,
    output wire signed [DATA_WIDTH-1:0]  taps_out [0:TAPS-1],
    output wire                          valid_out [0:TAPS-1]
);
    reg signed [DATA_WIDTH-1:0] mem  [0:TAPS-1];
    reg                         vld  [0:TAPS-1];
    integer i;

    always @(posedge clk) begin
        if (!rst_n) begin
            for (i = 0; i < TAPS; i = i + 1) begin
                mem[i] <= '0;
                vld[i] <= 1'b0;
            end
        end else if (valid_in) begin
            mem[0] <= d_in;
            vld[0] <= 1'b1;
            for (i = 1; i < TAPS; i = i + 1) begin
                mem[i] <= mem[i-1];
                vld[i] <= vld[i-1];
            end
        end
    end

    genvar g;
    generate
        for (g = 0; g < TAPS; g = g + 1) begin : tap_assign
            assign taps_out[g] = mem[g];
            assign valid_out[g] = vld[g];
        end
    endgenerate
endmodule

// ── Testbench ─────────────────────────────────────────────────────────────
module tb_shift_reg;

    localparam TAPS       = 8;    // Smaller than full FIR for clarity
    localparam DATA_WIDTH = 16;

    reg                          clk;
    reg                          rst_n;
    reg  signed [DATA_WIDTH-1:0] d_in;
    reg                          valid_in;
    wire signed [DATA_WIDTH-1:0] taps_out [0:TAPS-1];
    wire                         valid_out [0:TAPS-1];

    shift_reg #(.TAPS(TAPS), .DATA_WIDTH(DATA_WIDTH)) dut (
        .clk      (clk),
        .rst_n    (rst_n),
        .d_in     (d_in),
        .valid_in (valid_in),
        .taps_out (taps_out),
        .valid_out(valid_out)
    );

    initial clk = 0;
    always #10 clk = ~clk;

    initial begin
        $dumpfile("tb_shift_reg.vcd");
        $dumpvars(0, tb_shift_reg);
    end

    integer k, pass, fail;
    reg signed [DATA_WIDTH-1:0] snap0, snap1;

    task automatic check;
        input integer tap;
        input signed [DATA_WIDTH-1:0] expected;
        input [127:0] label;
        begin
            if (taps_out[tap] === expected) begin
                $display("  PASS [%0s] tap[%0d] = %0d", label, tap, taps_out[tap]);
                pass = pass + 1;
            end else begin
                $display("  FAIL [%0s] tap[%0d] = %0d  expected %0d", label, tap, taps_out[tap], expected);
                fail = fail + 1;
            end
        end
    endtask

    initial begin
        pass = 0; fail = 0;

        // ── Reset ────────────────────────────────────────
        rst_n = 0; valid_in = 0; d_in = 0;
        repeat(4) @(posedge clk);
        rst_n = 1; @(posedge clk);

        // ════════════════════════════════════════════════
        // TEST 1: All taps zero after reset
        // ════════════════════════════════════════════════
        $display("\n[TEST 1] All taps zero after reset");
        for (k = 0; k < TAPS; k = k + 1)
            check(k, 16'sh0000, "reset");

        // ════════════════════════════════════════════════
        // TEST 2: Single sample propagates through all taps
        //   Clock in 0xAAAA once, then zeros. Watch it shift.
        // ════════════════════════════════════════════════
        $display("\n[TEST 2] Single sample propagates through taps");
        @(posedge clk); d_in = 16'shAAAA; valid_in = 1;
        @(posedge clk); d_in = 16'sh0000;  // one pulse only

        repeat(TAPS - 1) begin : prop_loop
            integer tap_idx;
            // After each clock, the sample should be one tap deeper
            @(posedge clk);
            #1; // tiny settle
            tap_idx = 0; // sample is always at tap[0] after the first clock...
            // Actually check that tap[0] holds last value, tap[1] previous, etc.
        end
        valid_in = 0;

        // Feed TAPS distinct values and verify ordering
        $display("\n[TEST 3] FIFO ordering — newest at tap[0], oldest at tap[N-1]");
        rst_n = 0; repeat(2) @(posedge clk); rst_n = 1; @(posedge clk);
        valid_in = 1;
        for (k = 1; k <= TAPS; k = k + 1) begin
            @(posedge clk);
            d_in = k;   // push 1,2,3,...,TAPS
        end
        @(posedge clk); valid_in = 0;
        #1;

        // tap[0] = TAPS (newest), tap[TAPS-1] = 1 (oldest)
        check(0,       TAPS,  "ordering-newest");
        check(1,       TAPS-1,"ordering-2nd");
        check(TAPS-1,  1,     "ordering-oldest");

        // ════════════════════════════════════════════════
        // TEST 4: valid_in gating — tap values freeze when valid_in=0
        // ════════════════════════════════════════════════
        $display("\n[TEST 4] valid_in gating — values freeze when valid=0");
        rst_n = 0; repeat(2) @(posedge clk); rst_n = 1; @(posedge clk);

        @(posedge clk); d_in = 16'sh1234; valid_in = 1;
        @(posedge clk); d_in = 16'sh5678; valid_in = 1;
        @(posedge clk); valid_in = 0;     // gate off
        #1;
        begin
            snap0 = taps_out[0];
            snap1 = taps_out[1];
            repeat(5) @(posedge clk);
            #1;
            if (taps_out[0] === snap0 && taps_out[1] === snap1) begin
                $display("  PASS: tap values frozen while valid_in=0");
                pass = pass + 1;
            end else begin
                $display("  FAIL: taps changed while valid_in=0");
                fail = fail + 1;
            end
        end

        // ════════════════════════════════════════════════
        // TEST 5: Negative values propagate correctly (signed check)
        // ════════════════════════════════════════════════
        $display("\n[TEST 5] Negative (signed) values");
        rst_n = 0; repeat(2) @(posedge clk); rst_n = 1; @(posedge clk);
        valid_in = 1;
        @(posedge clk); d_in = -16'sh0001;   // -1
        @(posedge clk); d_in = -16'sh7FFF;   // most negative
        @(posedge clk); d_in =  16'sh7FFF;   // most positive
        @(posedge clk); valid_in = 0;
        #1;
        check(0,  16'sh7FFF, "signed-pos");
        check(1, -16'sh7FFF, "signed-neg-max");
        check(2, -16'sh0001, "signed-neg-one");

        // ════════════════════════════════════════════════
        // TEST 6: valid_out tracks valid_in pipeline
        // ════════════════════════════════════════════════
        $display("\n[TEST 6] valid_out propagates with data");
        rst_n = 0; repeat(2) @(posedge clk); rst_n = 1; @(posedge clk);

        if (!valid_out[0]) begin
            $display("  PASS: valid_out[0] starts low");
            pass = pass + 1;
        end else begin
            $display("  FAIL: valid_out[0] should start low");
            fail = fail + 1;
        end

        @(posedge clk); d_in = 16'sh0001; valid_in = 1;
        @(posedge clk); valid_in = 0;
        #1;
        if (valid_out[0]) begin
            $display("  PASS: valid_out[0] high after one valid push");
            pass = pass + 1;
        end else begin
            $display("  FAIL: valid_out[0] should be high");
            fail = fail + 1;
        end

        // ════════════════════════════════════════════════
        // TEST 7: Random input sequence
        // ════════════════════════════════════════════════
        $display("\n[TEST 7] Random input sequence");
        rst_n = 0; repeat(2) @(posedge clk); rst_n = 1; @(posedge clk);
        valid_in = 1;
        for (k = 0; k < 50; k = k + 1) begin
            d_in = $random & 16'hFFFF; // random 16-bit
            @(posedge clk);
        end
        valid_in = 0;
        $display("  PASS: Random sequence completed without error");
        pass = pass + 1;

        // ════════════════════════════════════════════════
        // TEST 8: X propagation
        // ════════════════════════════════════════════════
        $display("\n[TEST 8] X propagation");
        rst_n = 0; repeat(2) @(posedge clk); rst_n = 1; @(posedge clk);
        d_in = 16'hXXXX; valid_in = 1;
        @(posedge clk); valid_in = 0;
        #1;
        // Check that taps become X
        begin
            integer x_fail;
            x_fail = 0;
            for (k = 0; k < TAPS; k = k + 1) begin
                if (taps_out[k] !== 16'hXXXX) begin
                    $display("  FAIL: tap[%0d] not X after X input", k);
                    x_fail = 1;
                end
            end
            if (x_fail == 0) begin
                $display("  PASS: X propagated correctly");
                pass = pass + 1;
            end else begin
                fail = fail + 1;
            end
        end

        // ── Summary ──────────────────────────────────────
        $display("\n════════════════════════════════");
        $display("  shift_reg: %0d passed, %0d failed", pass, fail);
        $display("════════════════════════════════\n");
        $finish;
    end

    initial begin #500_000; $display("TIMEOUT"); $finish; end

endmodule

tb_shift_reg.vcd
$date
	Thu Apr 30 00:47:21 2026
$end
$version
	Icarus Verilog
$end
$timescale
	1ps
$end
$scope module tb_shift_reg $end
$var parameter 32 ! DATA_WIDTH $end
$var parameter 32 " TAPS $end
$var reg 1 # clk $end
$var reg 16 $ d_in [15:0] $end
$var reg 1 % rst_n $end
$var reg 16 & snap0 [15:0] $end
$var reg 16 ' snap1 [15:0] $end
$var reg 1 ( valid_in $end
$var integer 32 ) fail [31:0] $end
$var integer 32 * k [31:0] $end
$var integer 32 + pass [31:0] $end
$scope module dut $end
$var wire 1 # clk $end
$var wire 16 , d_in [15:0] $end
$var wire 1 % rst_n $end
$var wire 1 ( valid_in $end
$var parameter 32 - DATA_WIDTH $end
$var parameter 32 . TAPS $end
$var integer 32 / i [31:0] $end
$scope begin tap_assign[0] $end
$var parameter 2 0 g $end
$upscope $end
$scope begin tap_assign[1] $end
$var parameter 2 1 g $end
$upscope $end
$scope begin tap_assign[2] $end
$var parameter 3 2 g $end
$upscope $end
$scope begin tap_assign[3] $end
$var parameter 3 3 g $end
$upscope $end
$scope begin tap_assign[4] $end
$var parameter 4 4 g $end
$upscope $end
$scope begin tap_assign[5] $end
$var parameter 4 5 g $end
$upscope $end
$scope begin tap_assign[6] $end
$var parameter 4 6 g $end
$upscope $end
$scope begin tap_assign[7] $end
$var parameter 4 7 g $end
$upscope $end
$upscope $end
$scope begin $unm_blk_20 $end
$var integer 32 8 x_fail [31:0] $end
$upscope $end
$scope begin prop_loop $end
$var integer 32 9 tap_idx [31:0] $end
$upscope $end
$scope task check $end
$upscope $end
$upscope $end
$enddefinitions $end
$comment Show the parameter values. $end
$dumpall
b111 7
b110 6
b101 5
b100 4
b11 3
b10 2
b1 1
b0 0
b1000 .
b10000 -
b1000 "
b10000 !
$end
#0
$dumpvars
bx 9
bx 8
bx /
b0 ,
b0 +
bx *
b0 )
0(
bx '
bx &
0%
b0 $
0#
$end
#10000
b1000 /
1#
#20000
0#
#30000
b1000 /
1#
#40000
0#
#50000
b1000 /
1#
#60000
0#
#70000
1%
b1000 /
1#
#80000
0#
#90000
b1000 +
b1000 *
1#
#100000
0#
#110000
b1000 /
1(
b1010101010101010 $
b1010101010101010 ,
1#
#120000
0#
#130000
b0 $
b0 ,
b1000 /
1#
#140000
0#
#150000
b1000 /
1#
#151000
b0 9
#160000
0#
#170000
b1000 /
1#
#180000
0#
#190000
b1000 /
1#
#200000
0#
#210000
b1000 /
1#
#220000
0#
#230000
b1000 /
1#
#240000
0#
#250000
b1000 /
1#
#260000
0#
#270000
b1000 /
1#
#271000
0%
0(
#280000
0#
#290000
b1000 /
1#
#300000
0#
#310000
1%
b1000 /
1#
#320000
0#
#330000
b1000 /
b1 *
1(
1#
#340000
0#
#350000
b10 *
b1 $
b1 ,
b1000 /
1#
#360000
0#
#370000
b1000 /
b11 *
b10 $
b10 ,
1#
#380000
0#
#390000
b100 *
b11 $
b11 ,
b1000 /
1#
#400000
0#
#410000
b1000 /
b101 *
b100 $
b100 ,
1#
#420000
0#
#430000
b110 *
b101 $
b101 ,
b1000 /
1#
#440000
0#
#450000
b1000 /
b111 *
b110 $
b110 ,
1#
#460000
0#
#470000
b1000 *
b111 $
b111 ,
b1000 /
1#
#480000
0#
#490000
b1000 /
b1001 *
b1000 $
b1000 ,
1#
#500000
0#
#510000
0(
b1000 /
1#
#511000
0%
b10 )
b1001 +
#520000
0#
#530000
b1000 /
1#
#540000
0#
#550000
1%
b1000 /
1#
#560000
0#
#570000
1#
#580000
0#
#590000
1(
b1001000110100 $
b1001000110100 ,
1#
#600000
0#
#610000
b1000 /
b101011001111000 $
b101011001111000 ,
1#
#620000
0#
#630000
0(
b1000 /
1#
#631000
b101011001111000 '
b101011001111000 &
#640000
0#
#650000
1#
#660000
0#
#670000
1#
#680000
0#
#690000
1#
#700000
0#
#710000
1#
#720000
0#
#730000
1#
#731000
0%
b1010 +
#740000
0#
#750000
b1000 /
1#
#760000
0#
#770000
1%
b1000 /
1#
#780000
0#
#790000
b1000 /
1(
1#
#800000
0#
#810000
b1111111111111111 $
b1111111111111111 ,
b1000 /
1#
#820000
0#
#830000
b1000 /
b1000000000000001 $
b1000000000000001 ,
1#
#840000
0#
#850000
b111111111111111 $
b111111111111111 ,
b1000 /
1#
#860000
0#
#870000
0(
1#
#871000
0%
b1011 +
b100 )
#880000
0#
#890000
b1000 /
1#
#900000
0#
#910000
1%
b1000 /
1#
#920000
0#
#930000
b1100 +
1#
#940000
0#
#950000
1(
b1 $
b1 ,
1#
#960000
0#
#970000
0(
1#
#971000
0%
b101 )
#980000
0#
#990000
b1000 /
1#
#1000000
0#
#1010000
1%
b1000 /
1#
#1020000
0#
#1030000
b1000 /
b11010100100100 $
b11010100100100 ,
b0 *
1(
1#
#1040000
0#
#1050000
b101111010000001 $
b101111010000001 ,
b1 *
b1000 /
1#
#1060000
0#
#1070000
b1000 /
b1101011000001001 $
b1101011000001001 ,
b10 *
1#
#1080000
0#
#1090000
b101011001100011 $
b101011001100011 ,
b11 *
b1000 /
1#
#1100000
0#
#1110000
b1000 /
b111101100001101 $
b111101100001101 ,
b100 *
1#
#1120000
0#
#1130000
b1001100110001101 $
b1001100110001101 ,
b101 *
b1000 /
1#
#1140000
0#
#1150000
b1000 /
b1000010001100101 $
b1000010001100101 ,
b110 *
1#
#1160000
0#
#1170000
b101001000010010 $
b101001000010010 ,
b111 *
b1000 /
1#
#1180000
0#
#1190000
b1000 /
b1110001100000001 $
b1110001100000001 ,
b1000 *
1#
#1200000
0#
#1210000
b1100110100001101 $
b1100110100001101 ,
b1001 *
b1000 /
1#
#1220000
0#
#1230000
b1000 /
b1111000101110110 $
b1111000101110110 ,
b1010 *
1#
#1240000
0#
#1250000
b1100110100111101 $
b1100110100111101 ,
b1011 *
b1000 /
1#
#1260000
0#
#1270000
b1000 /
b101011111101101 $
b101011111101101 ,
b1100 *
1#
#1280000
0#
#1290000
b1111011110001100 $
b1111011110001100 ,
b1101 *
b1000 /
1#
#1300000
0#
#1310000
b1000 /
b1110100111111001 $
b1110100111111001 ,
b1110 *
1#
#1320000
0#
#1330000
b10010011000110 $
b10010011000110 ,
b1111 *
b1000 /
1#
#1340000
0#
#1350000
b1000 /
b1000010011000101 $
b1000010011000101 ,
b10000 *
1#
#1360000
0#
#1370000
b1101001010101010 $
b1101001010101010 ,
b10001 *
b1000 /
1#
#1380000
0#
#1390000
b1000 /
b1111011111100101 $
b1111011111100101 ,
b10010 *
1#
#1400000
0#
#1410000
b111001001110111 $
b111001001110111 ,
b10011 *
b1000 /
1#
#1420000
0#
#1430000
b1000 /
b1101011000010010 $
b1101011000010010 ,
b10100 *
1#
#1440000
0#
#1450000
b1101101110001111 $
b1101101110001111 ,
b10101 *
b1000 /
1#
#1460000
0#
#1470000
b1000 /
b110100111110010 $
b110100111110010 ,
b10110 *
1#
#1480000
0#
#1490000
b1001011011001110 $
b1001011011001110 ,
b10111 *
b1000 /
1#
#1500000
0#
#1510000
b1000 /
b111101011101000 $
b111101011101000 ,
b11000 *
1#
#1520000
0#
#1530000
b100111011000101 $
b100111011000101 ,
b11001 *
b1000 /
1#
#1540000
0#
#1550000
b1000 /
b100100101011100 $
b100100101011100 ,
b11010 *
1#
#1560000
0#
#1570000
b10100010111101 $
b10100010111101 ,
b11011 *
b1000 /
1#
#1580000
0#
#1590000
b1000 /
b101100000101101 $
b101100000101101 ,
b11100 *
1#
#1600000
0#
#1610000
b10011001100101 $
b10011001100101 ,
b11101 *
b1000 /
1#
#1620000
0#
#1630000
b1000 /
b110001001100011 $
b110001001100011 ,
b11110 *
1#
#1640000
0#
#1650000
b1000011100001010 $
b1000011100001010 ,
b11111 *
b1000 /
1#
#1660000
0#
#1670000
b1000 /
b10001010000000 $
b10001010000000 ,
b100000 *
1#
#1680000
0#
#1690000
b10000100100000 $
b10000100100000 ,
b100001 *
b1000 /
1#
#1700000
0#
#1710000
b1000 /
b100010110101010 $
b100010110101010 ,
b100010 *
1#
#1720000
0#
#1730000
b1100110010011101 $
b1100110010011101 ,
b100011 *
b1000 /
1#
#1740000
0#
#1750000
b1000 /
b11111010010110 $
b11111010010110 ,
b100100 *
1#
#1760000
0#
#1770000
b1011100000010011 $
b1011100000010011 ,
b100101 *
b1000 /
1#
#1780000
0#
#1790000
b1000 /
b11100000001101 $
b11100000001101 ,
b100110 *
1#
#1800000
0#
#1810000
b1101011001010011 $
b1101011001010011 ,
b100111 *
b1000 /
1#
#1820000
0#
#1830000
b1000 /
b1101110101101011 $
b1101110101101011 ,
b101000 *
1#
#1840000
0#
#1850000
b10101011010101 $
b10101011010101 ,
b101001 *
b1000 /
1#
#1860000
0#
#1870000
b1000 /
b100101000000010 $
b100101000000010 ,
b101010 *
1#
#1880000
0#
#1890000
b11111010101110 $
b11111010101110 ,
b101011 *
b1000 /
1#
#1900000
0#
#1910000
b1000 /
b1110100100011101 $
b1110100100011101 ,
b101100 *
1#
#1920000
0#
#1930000
b111001011001111 $
b111001011001111 ,
b101101 *
b1000 /
1#
#1940000
0#
#1950000
b1000 /
b100100100100011 $
b100100100100011 ,
b101110 *
1#
#1960000
0#
#1970000
b110010100001010 $
b110010100001010 ,
b101111 *
b1000 /
1#
#1980000
0#
#1990000
b1000 /
b101011001010 $
b101011001010 ,
b110000 *
1#
#2000000
0#
#2010000
b100110000111100 $
b100110000111100 ,
b110001 *
b1000 /
1#
#2020000
0#
#2030000
b1000 /
0%
b1101 +
0(
b110010 *
1#
#2040000
0#
#2050000
b1000 /
1#
#2060000
0#
#2070000
1%
1#
#2080000
0#
#2090000
1(
bx $
bx ,
1#
#2100000
0#
#2110000
0(
1#
#2111000
b110 )
b1000 *
b1 8
